jsview/__init__.py
jsview/jsview.py
jsview-1.0.dist-info/DESCRIPTION.rst
jsview-1.0.dist-info/METADATA
jsview-1.0.dist-info/RECORD
jsview-1.0.dist-info/WHEEL
jsview-1.0.dist-info/entry_points.txt
jsview-1.0.dist-info/metadata.json
jsview-1.0.dist-info/top_level.txt
