Metadata-Version: 2.0
Name: jsview
Version: 1.0
Summary: A smarter JSON indenter
Home-page: https://github.com/fab13n/jsview
Author: Fabien Fleutot
Author-email: fleutot+jsview@gmail.com
License: UNKNOWN
Platform: UNKNOWN
Classifier: Programming Language :: Python :: 2
Classifier: License :: OSI Approved :: MIT License
Classifier: Operating System :: OS Independent
